hemlock_big5/__init__.py
hemlock_big5/bfi10.yaml
hemlock_big5/ipip50.yaml
hemlock_big5/tipi.yaml
hemlock_big5-0.0.2.dist-info/LICENSE
hemlock_big5-0.0.2.dist-info/METADATA
hemlock_big5-0.0.2.dist-info/WHEEL
hemlock_big5-0.0.2.dist-info/top_level.txt
hemlock_big5-0.0.2.dist-info/RECORD
