Metadata-Version: 2.1
Name: hemlock-big5
Version: 0.0.2
Summary: Hemlock extension for the big 5 personality inventory
Home-page: https://dsbowen.github.io/hemlock-big5
Author: Dillon Bowen
Author-email: dsbowen@wharton.upenn.edu
License: UNKNOWN
Platform: UNKNOWN
Classifier: Programming Language :: Python :: 3
Classifier: License :: OSI Approved :: MIT License
Classifier: Operating System :: OS Independent
Requires-Python: >=3.6
Requires-Dist: pyyaml
Requires-Dist: hemlock-survey (>=0.0.51)
